src/__init__.py
src/constants.py
src/migrate.py
tests/__init__.py
tests/test_migratedatabase.py
rdbmpy-1.0.12.dist-info/LICENSE.txt
rdbmpy-1.0.12.dist-info/METADATA
rdbmpy-1.0.12.dist-info/WHEEL
rdbmpy-1.0.12.dist-info/entry_points.txt
rdbmpy-1.0.12.dist-info/top_level.txt
rdbmpy-1.0.12.dist-info/RECORD
