Metadata-Version: 2.1
Name: rdbmpy
Version: 1.0.12
Summary: A Python package for managing database migrations with PostgreSQL, MySQL, and SQL Server
Home-page: https://github.com/gdakuzak/rdbmpy
Author: Guilherme Makoto Sacoman Dakuzaku
Author-email: makoto@rocketti.com.br
License: Apache License
Keywords: database,migration,postgresql,mysql,sqlserver,orm,sqlalchemy
Classifier: Development Status :: 3 - Alpha
Classifier: Intended Audience :: Developers
Classifier: Programming Language :: Python :: 3
Requires-Python: >=3.6
License-File: LICENSE.txt
Requires-Dist: greenlet >=1.1.0
Requires-Dist: psycopg[binary] >=3.1
Requires-Dist: python-dotenv >=0.10.2
Requires-Dist: SQLAlchemy >=1.3.17
Requires-Dist: pymysql >=1.0.0
Provides-Extra: sqlserver
Requires-Dist: pyodbc >=4.0.39 ; extra == 'sqlserver'
